{
  "colorOrder": {
    "F(M)フリー": 1,
    "Sサイズ": 1,
    "Mサイズ": 2,
    "Lサイズ": 3,
    "ホワイト": 1,
    "オフホワイト": 2,
    "オートミール": 3,
    "アイボリー": 4,
    "クリーム": 5,
    "クリーム×イエロー": 6,
    "ライトベージュ": 7,
    "ベージュ": 8,
    "ライトブルー": 9,
    "ピンク": 10,
    "イエロー": 11,
    "バターイエロー": 12,
    "ブルー": 13,
    "ミント": 14,
    "ミントグレー": 15,
    "ベージュ×ブラック": 16,
    "グレー×ブルー": 17,
    "グレージュ": 18,
    "グレージュ×ピンク": 19,
    "ブラウン": 20,
    "ブラウンMIX": 21,
    "チャコール": 22,
    "チャコールMIX": 23,
    "ブラック": 9999,
    "スミクロ": 9999,
    "クリームイエロー": 6,
    "ダークブラウン": 21
  },
  "nameCleanPatterns": [
    "《[^》]*》",
    "【メール便】",
    "\\s*\\d{6}$"
  ],
  "deleteTemplates": [
    "<!--配送について-->",
    "<!--ご注意-->",
    "<!--レビューを書いて-->",
    "<!--コンセプト-->",
    "<!--よくある質問-->"
  ],
  "malls": {
    "rakuten": {
      "controlCol": "n",
      "genreId": "",
      "catalogReason": "3",
      "stockType": "1",
      "restockBtn": "0",
      "rakutenAppId": "feb7b7ce-bd14-47f7-be51-82fc8375e35f",
      "shippingCat1": "",
      "shippingCat2": "",
      "shipLeadtime": "",
      "deliveryLeadtime": "",
      "okihai": "",
      "namePrefix": "NOAHL｜",
      "nameSuffix": "",
      "priceRate": 40,
      "taxType": "0",
      "pointRate": 1,
      "pointStart": "",
      "pointEnd": "",
      "shippingFee": "0",
      "indivShipping": 0,
      "shippingSet": "1",
      "shippingName": "宅急便(ヤマト運輸)",
      "shippingSets": [
        {
          "num": "1",
          "name": "宅急便(ヤマト運輸)"
        },
        {
          "num": "2",
          "name": "ネコポス(ヤマト運輸)"
        },
        {
          "num": "3",
          "name": "ゆうパック(日本郵政)"
        },
        {
          "num": "4",
          "name": "ゆうパケット(日本郵政)"
        }
      ],
      "asuraku": "",
      "deliveryInfo": "",
      "noshi": "0",
      "pcDescTpl": "【商品紹介】<br>\n\n【サイズ】<br>\n{採寸サイズ整形}<br><br>\n\n【モデル着用サイズ / 身長】<br>\n\n\n【素材】<br>\n{素材}<br><br>\n\n【カラー】<br>\n{カラー一覧}<br><br>\n\n【備考】<br>\n ・ポケットなし / 透け感あり / 伸縮性なし / 裏地なし<br>\n ※ご利用の端末環境により、商品画像と実物では多少色合いが異なって見える場合がございます。<br>\n ※お洗濯、アイロンの際は内タグの品質表示を必ずご確認ください。<br>\n ※商品にはたたみシワ等のシワがついている場合がございます。<br>\n ※染料による匂いが抜けきれず、特有の匂いがする場合がございます。<br>",
      "spDescTpl": "",
      "saleDescTpl": "",
      "imgCabinet": "",
      "imgType": "0",
      "imgCabinetBase": "/shohin/",
      "maxProductImages": 20
    },
    "shopline": {
      "priceRate": 100,
      "defaultStock": 0,
      "namePrefix": "",
      "nameSuffix": ""
    },
    "yahoo": {
      "priceRate": 40,
      "namePrefix": "",
      "nameSuffix": ""
    },
    "amazon": {
      "priceRate": 100,
      "brand": "",
      "namePrefix": "",
      "nameSuffix": ""
    },
    "qoo10": {
      "priceRate": 100,
      "namePrefix": "",
      "nameSuffix": ""
    }
  }
}